MANIFEST.in
README.md
requirements.txt
setup.py
elsp_drl.egg-info/PKG-INFO
elsp_drl.egg-info/SOURCES.txt
elsp_drl.egg-info/dependency_links.txt
elsp_drl.egg-info/top_level.txt
experiment/__init__.py
experiment/oyebolu2019/__init__.py
experiment/oyebolu2019/env_create.py
experiment/oyebolu2019/standard_self_attention/__init__.py
experiment/oyebolu2019/standard_self_attention/elsp_callback.py
experiment/oyebolu2019/standard_self_attention/run.py
experiment/oyebolu2019/standard_self_attention/module/__init__.py
experiment/oyebolu2019/standard_self_attention/module/set_transformer.py
hook/__init__.py
hook/hook.py
modules/__init__.py
modules/set_transformer/__init__.py
modules/set_transformer/models.py