Metadata-Version: 1.0
Name: elsp-drl
Version: 0.0.1
Summary: elsp drl
Home-page: https://github.com/Meeea-914/elsp_drl
Author: Meeea-914
Author-email: 1028634300@qq.com
License: MIT Licence
Keywords: pip,elsp,drl
Platform: any
